ensures/__init__.py
ensures/ensures.py
ensures/examples.py
ensures/test_benchmarks.py
ensures/test_property_based.py
ensures/tests.py
ensures-0.3.0.dist-info/licenses/LICENSE
ensures-0.3.0.dist-info/WHEEL
ensures-0.3.0.dist-info/METADATA
ensures-0.3.0.dist-info/RECORD
