Metadata-Version: 2.4
Name: ensures
Version: 0.3.0
Summary: Design by Contract with Functional Programming
Keywords: design-by-contract,precondition,postcondition,invariant,testing,validation
Author: Bruno Dantas
Author-email: Bruno Dantas <4422988+brunodantas@users.noreply.github.com>
License-Expression: GPL-3.0-or-later
License-File: LICENSE
Classifier: Development Status :: 4 - Beta
Classifier: Intended Audience :: Developers
Classifier: Topic :: Software Development :: Libraries :: Python Modules
Classifier: Topic :: Software Development :: Quality Assurance
Classifier: Topic :: Software Development :: Testing
Classifier: Programming Language :: Python :: 3
Classifier: Programming Language :: Python :: 3.10
Classifier: Programming Language :: Python :: 3.11
Classifier: Programming Language :: Python :: 3.12
Classifier: Programming Language :: Python :: 3.13
Classifier: Operating System :: OS Independent
Classifier: Typing :: Typed
Requires-Python: >=3.10
Project-URL: Changelog, https://github.com/brunodantas/ensures/blob/main/CHANGELOG.md
Project-URL: Documentation, https://github.com/brunodantas/ensures#readme
Project-URL: Homepage, https://github.com/brunodantas/ensures
Project-URL: Issues, https://github.com/brunodantas/ensures/issues
Project-URL: Repository, https://github.com/brunodantas/ensures
